wenda_gpu/LBFGS.py
wenda_gpu/LBFGS_utils.py
wenda_gpu/utils.py
wenda_gpu/wenda_gpu.py
wenda_gpu-0.7.5.dist-info/LICENSE
wenda_gpu-0.7.5.dist-info/METADATA
wenda_gpu-0.7.5.dist-info/WHEEL
wenda_gpu-0.7.5.dist-info/top_level.txt
wenda_gpu-0.7.5.dist-info/RECORD
