Metadata-Version: 2.1
Name: wenda-gpu
Version: 0.7.5
Summary: Fast domain adaptation for genomic data
Home-page: https://github.com/greenelab/wenda_gpu
Author: Ariel Hippen
Author-email: ariel.hippen@gmail.com
License: BSD 3-Clause
Requires-Python: >=3.7
License-File: LICENSE
Requires-Dist: pandas
Requires-Dist: numpy
Requires-Dist: torchvision
Requires-Dist: scipy
Requires-Dist: matplotlib
Requires-Dist: gpytorch (>=1.5.0)
Requires-Dist: glmnet (>=2.0)
